{
  "prediction_date": "2026-06-17",
  "config": "JMA_Full+GPS",
  "data_hashes": {
    "usgs": "f0bb7cd19bbd9a68",
    "jma": "74944a3ab2ae0d4d",
    "gps": "2235c9233626bf48"
  },
  "zones": [
    {
      "zone_id": "Z_15_120",
      "name": "Okinawa",
      "pop_millions": 28,
      "tiers": {
        "T1": {
          "probability": 0.007101,
          "alerts": {
            "0.5pct": false,
            "1.0pct": false,
            "2.0pct": false,
            "5.0pct": false,
            "10.0pct": false
          },
          "validity": {
            "window_days": 2,
            "valid_from": "2026-06-18T00:00:00Z",
            "valid_to": "2026-06-19T23:59:59Z"
          },
          "probability_seismic": 0.007101,
          "gps_reliability": 0.646,
          "boost": 0.0
        },
        "T2": {
          "probability": 0.131787,
          "alerts": {
            "0.5pct": false,
            "1.0pct": false,
            "2.0pct": false,
            "5.0pct": false,
            "10.0pct": false
          },
          "validity": {
            "window_days": 2,
            "valid_from": "2026-06-18T00:00:00Z",
            "valid_to": "2026-06-19T23:59:59Z"
          },
          "probability_seismic": 0.131787,
          "gps_reliability": 0.646,
          "boost": 0.0
        },
        "T3": {
          "probability": 0.295858,
          "alerts": {
            "0.5pct": false,
            "1.0pct": false,
            "2.0pct": false,
            "5.0pct": false,
            "10.0pct": false
          },
          "validity": {
            "window_days": 3,
            "valid_from": "2026-06-18T00:00:00Z",
            "valid_to": "2026-06-20T23:59:59Z"
          },
          "probability_seismic": 0.295858,
          "gps_reliability": 0.646,
          "boost": 0.0
        },
        "T4": {
          "probability": 0.324966,
          "alerts": {
            "0.5pct": false,
            "1.0pct": false,
            "2.0pct": false,
            "5.0pct": false,
            "10.0pct": false
          },
          "validity": {
            "window_days": 3,
            "valid_from": "2026-06-18T00:00:00Z",
            "valid_to": "2026-06-20T23:59:59Z"
          },
          "probability_seismic": 0.324966,
          "gps_reliability": 0.646,
          "boost": 0.0
        }
      }
    },
    {
      "zone_id": "Z_15_145",
      "name": "Z_15_145",
      "pop_millions": 0,
      "tiers": {
        "T1": {
          "probability": 0.007154,
          "alerts": {
            "0.5pct": false,
            "1.0pct": false,
            "2.0pct": false,
            "5.0pct": false,
            "10.0pct": false
          },
          "validity": {
            "window_days": 2,
            "valid_from": "2026-06-18T00:00:00Z",
            "valid_to": "2026-06-19T23:59:59Z"
          },
          "probability_seismic": 0.007154,
          "gps_reliability": 0.25,
          "boost": 0.0
        },
        "T2": {
          "probability": 0.132406,
          "alerts": {
            "0.5pct": false,
            "1.0pct": false,
            "2.0pct": false,
            "5.0pct": false,
            "10.0pct": false
          },
          "validity": {
            "window_days": 2,
            "valid_from": "2026-06-18T00:00:00Z",
            "valid_to": "2026-06-19T23:59:59Z"
          },
          "probability_seismic": 0.132406,
          "gps_reliability": 0.25,
          "boost": 0.0
        },
        "T3": {
          "probability": 0.296338,
          "alerts": {
            "0.5pct": false,
            "1.0pct": false,
            "2.0pct": false,
            "5.0pct": false,
            "10.0pct": false
          },
          "validity": {
            "window_days": 3,
            "valid_from": "2026-06-18T00:00:00Z",
            "valid_to": "2026-06-20T23:59:59Z"
          },
          "probability_seismic": 0.296338,
          "gps_reliability": 0.25,
          "boost": 0.0
        },
        "T4": {
          "probability": 0.325346,
          "alerts": {
            "0.5pct": false,
            "1.0pct": false,
            "2.0pct": false,
            "5.0pct": false,
            "10.0pct": false
          },
          "validity": {
            "window_days": 3,
            "valid_from": "2026-06-18T00:00:00Z",
            "valid_to": "2026-06-20T23:59:59Z"
          },
          "probability_seismic": 0.325346,
          "gps_reliability": 0.25,
          "boost": 0.0
        }
      }
    },
    {
      "zone_id": "Z_20_120",
      "name": "Ryukyu",
      "pop_millions": 8,
      "tiers": {
        "T1": {
          "probability": 0.541275,
          "alerts": {
            "0.5pct": false,
            "1.0pct": false,
            "2.0pct": false,
            "5.0pct": false,
            "10.0pct": false
          },
          "validity": {
            "window_days": 2,
            "valid_from": "2026-06-18T00:00:00Z",
            "valid_to": "2026-06-19T23:59:59Z"
          },
          "probability_seismic": 0.541275,
          "gps_reliability": 0.25,
          "boost": 0.0
        },
        "T2": {
          "probability": 0.334011,
          "alerts": {
            "0.5pct": false,
            "1.0pct": false,
            "2.0pct": false,
            "5.0pct": false,
            "10.0pct": false
          },
          "validity": {
            "window_days": 2,
            "valid_from": "2026-06-18T00:00:00Z",
            "valid_to": "2026-06-19T23:59:59Z"
          },
          "probability_seismic": 0.334011,
          "gps_reliability": 0.25,
          "boost": 0.0
        },
        "T3": {
          "probability": 0.055733,
          "alerts": {
            "0.5pct": false,
            "1.0pct": false,
            "2.0pct": false,
            "5.0pct": false,
            "10.0pct": false
          },
          "validity": {
            "window_days": 3,
            "valid_from": "2026-06-18T00:00:00Z",
            "valid_to": "2026-06-20T23:59:59Z"
          },
          "probability_seismic": 0.055733,
          "gps_reliability": 0.25,
          "boost": -0.0
        },
        "T4": {
          "probability": 0.003799,
          "alerts": {
            "0.5pct": false,
            "1.0pct": false,
            "2.0pct": false,
            "5.0pct": false,
            "10.0pct": false
          },
          "validity": {
            "window_days": 3,
            "valid_from": "2026-06-18T00:00:00Z",
            "valid_to": "2026-06-20T23:59:59Z"
          },
          "probability_seismic": 0.003799,
          "gps_reliability": 0.25,
          "boost": 0.0
        }
      }
    },
    {
      "zone_id": "Z_20_125",
      "name": "Z_20_125",
      "pop_millions": 0,
      "tiers": {
        "T1": {
          "probability": 0.336842,
          "alerts": {
            "0.5pct": false,
            "1.0pct": false,
            "2.0pct": false,
            "5.0pct": false,
            "10.0pct": false
          },
          "validity": {
            "window_days": 2,
            "valid_from": "2026-06-18T00:00:00Z",
            "valid_to": "2026-06-19T23:59:59Z"
          },
          "probability_seismic": 0.336842,
          "gps_reliability": 0.25,
          "boost": 0.0
        },
        "T2": {
          "probability": 0.306573,
          "alerts": {
            "0.5pct": false,
            "1.0pct": false,
            "2.0pct": false,
            "5.0pct": false,
            "10.0pct": false
          },
          "validity": {
            "window_days": 2,
            "valid_from": "2026-06-18T00:00:00Z",
            "valid_to": "2026-06-19T23:59:59Z"
          },
          "probability_seismic": 0.306573,
          "gps_reliability": 0.25,
          "boost": 0.0
        },
        "T3": {
          "probability": 0.15486,
          "alerts": {
            "0.5pct": false,
            "1.0pct": false,
            "2.0pct": false,
            "5.0pct": false,
            "10.0pct": false
          },
          "validity": {
            "window_days": 3,
            "valid_from": "2026-06-18T00:00:00Z",
            "valid_to": "2026-06-20T23:59:59Z"
          },
          "probability_seismic": 0.15486,
          "gps_reliability": 0.25,
          "boost": 0.0
        },
        "T4": {
          "probability": 0.127375,
          "alerts": {
            "0.5pct": false,
            "1.0pct": false,
            "2.0pct": false,
            "5.0pct": true,
            "10.0pct": true
          },
          "validity": {
            "window_days": 3,
            "valid_from": "2026-06-18T00:00:00Z",
            "valid_to": "2026-06-20T23:59:59Z"
          },
          "probability_seismic": 0.127375,
          "gps_reliability": 0.25,
          "boost": 0.0
        }
      }
    },
    {
      "zone_id": "Z_20_140",
      "name": "Z_20_140",
      "pop_millions": 0,
      "tiers": {
        "T1": {
          "probability": 0.025366,
          "alerts": {
            "0.5pct": false,
            "1.0pct": false,
            "2.0pct": false,
            "5.0pct": false,
            "10.0pct": false
          },
          "validity": {
            "window_days": 2,
            "valid_from": "2026-06-18T00:00:00Z",
            "valid_to": "2026-06-19T23:59:59Z"
          },
          "probability_seismic": 0.025366,
          "gps_reliability": 0.396,
          "boost": -0.0
        },
        "T2": {
          "probability": 0.201214,
          "alerts": {
            "0.5pct": false,
            "1.0pct": false,
            "2.0pct": false,
            "5.0pct": false,
            "10.0pct": false
          },
          "validity": {
            "window_days": 2,
            "valid_from": "2026-06-18T00:00:00Z",
            "valid_to": "2026-06-19T23:59:59Z"
          },
          "probability_seismic": 0.201214,
          "gps_reliability": 0.396,
          "boost": -0.0
        },
        "T3": {
          "probability": 0.337836,
          "alerts": {
            "0.5pct": false,
            "1.0pct": false,
            "2.0pct": false,
            "5.0pct": false,
            "10.0pct": false
          },
          "validity": {
            "window_days": 3,
            "valid_from": "2026-06-18T00:00:00Z",
            "valid_to": "2026-06-20T23:59:59Z"
          },
          "probability_seismic": 0.337836,
          "gps_reliability": 0.396,
          "boost": 0.0
        },
        "T4": {
          "probability": 0.362917,
          "alerts": {
            "0.5pct": false,
            "1.0pct": false,
            "2.0pct": false,
            "5.0pct": false,
            "10.0pct": false
          },
          "validity": {
            "window_days": 3,
            "valid_from": "2026-06-18T00:00:00Z",
            "valid_to": "2026-06-20T23:59:59Z"
          },
          "probability_seismic": 0.362917,
          "gps_reliability": 0.396,
          "boost": 0.0
        }
      }
    },
    {
      "zone_id": "Z_20_145",
      "name": "Z_20_145",
      "pop_millions": 0,
      "tiers": {
        "T1": {
          "probability": 0.074724,
          "alerts": {
            "0.5pct": false,
            "1.0pct": false,
            "2.0pct": false,
            "5.0pct": true,
            "10.0pct": true
          },
          "validity": {
            "window_days": 2,
            "valid_from": "2026-06-18T00:00:00Z",
            "valid_to": "2026-06-19T23:59:59Z"
          }
        },
        "T2": {
          "probability": 0.390967,
          "alerts": {
            "0.5pct": false,
            "1.0pct": false,
            "2.0pct": false,
            "5.0pct": true,
            "10.0pct": true
          },
          "validity": {
            "window_days": 2,
            "valid_from": "2026-06-18T00:00:00Z",
            "valid_to": "2026-06-19T23:59:59Z"
          }
        },
        "T3": {
          "probability": 0.380179,
          "alerts": {
            "0.5pct": false,
            "1.0pct": false,
            "2.0pct": false,
            "5.0pct": false,
            "10.0pct": true
          },
          "validity": {
            "window_days": 3,
            "valid_from": "2026-06-18T00:00:00Z",
            "valid_to": "2026-06-20T23:59:59Z"
          }
        },
        "T4": {
          "probability": 0.044321,
          "alerts": {
            "0.5pct": false,
            "1.0pct": false,
            "2.0pct": false,
            "5.0pct": false,
            "10.0pct": false
          },
          "validity": {
            "window_days": 3,
            "valid_from": "2026-06-18T00:00:00Z",
            "valid_to": "2026-06-20T23:59:59Z"
          }
        }
      }
    },
    {
      "zone_id": "Z_25_120",
      "name": "Z_25_120",
      "pop_millions": 2,
      "tiers": {
        "T1": {
          "probability": 0.088378,
          "alerts": {
            "0.5pct": false,
            "1.0pct": false,
            "2.0pct": false,
            "5.0pct": false,
            "10.0pct": false
          },
          "validity": {
            "window_days": 2,
            "valid_from": "2026-06-18T00:00:00Z",
            "valid_to": "2026-06-19T23:59:59Z"
          },
          "probability_seismic": 0.088378,
          "gps_reliability": 0.896,
          "boost": -0.0
        },
        "T2": {
          "probability": 0.167584,
          "alerts": {
            "0.5pct": false,
            "1.0pct": false,
            "2.0pct": false,
            "5.0pct": false,
            "10.0pct": false
          },
          "validity": {
            "window_days": 2,
            "valid_from": "2026-06-18T00:00:00Z",
            "valid_to": "2026-06-19T23:59:59Z"
          },
          "probability_seismic": 0.167584,
          "gps_reliability": 0.896,
          "boost": 0.0
        },
        "T3": {
          "probability": 0.024013,
          "alerts": {
            "0.5pct": false,
            "1.0pct": false,
            "2.0pct": false,
            "5.0pct": false,
            "10.0pct": false
          },
          "validity": {
            "window_days": 3,
            "valid_from": "2026-06-18T00:00:00Z",
            "valid_to": "2026-06-20T23:59:59Z"
          },
          "probability_seismic": 0.024013,
          "gps_reliability": 0.896,
          "boost": 0.0
        },
        "T4": {
          "probability": 0.000442,
          "alerts": {
            "0.5pct": false,
            "1.0pct": false,
            "2.0pct": false,
            "5.0pct": false,
            "10.0pct": false
          },
          "validity": {
            "window_days": 3,
            "valid_from": "2026-06-18T00:00:00Z",
            "valid_to": "2026-06-20T23:59:59Z"
          },
          "probability_seismic": 0.000442,
          "gps_reliability": 0.896,
          "boost": 0.0
        }
      }
    },
    {
      "zone_id": "Z_25_125",
      "name": "Z_25_125",
      "pop_millions": 0,
      "tiers": {
        "T1": {
          "probability": 0.275261,
          "alerts": {
            "0.5pct": false,
            "1.0pct": false,
            "2.0pct": false,
            "5.0pct": false,
            "10.0pct": false
          },
          "validity": {
            "window_days": 2,
            "valid_from": "2026-06-18T00:00:00Z",
            "valid_to": "2026-06-19T23:59:59Z"
          },
          "probability_seismic": 0.275261,
          "gps_reliability": 0.396,
          "boost": 0.0
        },
        "T2": {
          "probability": 0.084692,
          "alerts": {
            "0.5pct": false,
            "1.0pct": false,
            "2.0pct": false,
            "5.0pct": false,
            "10.0pct": false
          },
          "validity": {
            "window_days": 2,
            "valid_from": "2026-06-18T00:00:00Z",
            "valid_to": "2026-06-19T23:59:59Z"
          },
          "probability_seismic": 0.084692,
          "gps_reliability": 0.396,
          "boost": 0.0
        },
        "T3": {
          "probability": 0.003739,
          "alerts": {
            "0.5pct": false,
            "1.0pct": false,
            "2.0pct": false,
            "5.0pct": false,
            "10.0pct": false
          },
          "validity": {
            "window_days": 3,
            "valid_from": "2026-06-18T00:00:00Z",
            "valid_to": "2026-06-20T23:59:59Z"
          },
          "probability_seismic": 0.003739,
          "gps_reliability": 0.396,
          "boost": -0.0
        },
        "T4": {
          "probability": 3.7e-05,
          "alerts": {
            "0.5pct": false,
            "1.0pct": false,
            "2.0pct": false,
            "5.0pct": false,
            "10.0pct": false
          },
          "validity": {
            "window_days": 3,
            "valid_from": "2026-06-18T00:00:00Z",
            "valid_to": "2026-06-20T23:59:59Z"
          },
          "probability_seismic": 3.7e-05,
          "gps_reliability": 0.396,
          "boost": -0.0
        }
      }
    },
    {
      "zone_id": "Z_25_130",
      "name": "Z_25_130",
      "pop_millions": 0,
      "tiers": {
        "T1": {
          "probability": 0.348554,
          "alerts": {
            "0.5pct": false,
            "1.0pct": false,
            "2.0pct": false,
            "5.0pct": false,
            "10.0pct": false
          },
          "validity": {
            "window_days": 2,
            "valid_from": "2026-06-18T00:00:00Z",
            "valid_to": "2026-06-19T23:59:59Z"
          },
          "probability_seismic": 0.348554,
          "gps_reliability": 0.5,
          "boost": 0.0
        },
        "T2": {
          "probability": 0.326407,
          "alerts": {
            "0.5pct": false,
            "1.0pct": false,
            "2.0pct": false,
            "5.0pct": false,
            "10.0pct": false
          },
          "validity": {
            "window_days": 2,
            "valid_from": "2026-06-18T00:00:00Z",
            "valid_to": "2026-06-19T23:59:59Z"
          },
          "probability_seismic": 0.326407,
          "gps_reliability": 0.5,
          "boost": 0.0
        },
        "T3": {
          "probability": 0.087281,
          "alerts": {
            "0.5pct": false,
            "1.0pct": false,
            "2.0pct": false,
            "5.0pct": false,
            "10.0pct": false
          },
          "validity": {
            "window_days": 3,
            "valid_from": "2026-06-18T00:00:00Z",
            "valid_to": "2026-06-20T23:59:59Z"
          },
          "probability_seismic": 0.087281,
          "gps_reliability": 0.5,
          "boost": 0.0
        },
        "T4": {
          "probability": 0.041208,
          "alerts": {
            "0.5pct": false,
            "1.0pct": false,
            "2.0pct": false,
            "5.0pct": false,
            "10.0pct": false
          },
          "validity": {
            "window_days": 3,
            "valid_from": "2026-06-18T00:00:00Z",
            "valid_to": "2026-06-20T23:59:59Z"
          },
          "probability_seismic": 0.041208,
          "gps_reliability": 0.5,
          "boost": 0.0
        }
      }
    },
    {
      "zone_id": "Z_25_135",
      "name": "Z_25_135",
      "pop_millions": 0,
      "tiers": {
        "T1": {
          "probability": 0.234305,
          "alerts": {
            "0.5pct": false,
            "1.0pct": false,
            "2.0pct": false,
            "5.0pct": false,
            "10.0pct": false
          },
          "validity": {
            "window_days": 2,
            "valid_from": "2026-06-18T00:00:00Z",
            "valid_to": "2026-06-19T23:59:59Z"
          }
        },
        "T2": {
          "probability": 0.31725,
          "alerts": {
            "0.5pct": false,
            "1.0pct": false,
            "2.0pct": false,
            "5.0pct": false,
            "10.0pct": false
          },
          "validity": {
            "window_days": 2,
            "valid_from": "2026-06-18T00:00:00Z",
            "valid_to": "2026-06-19T23:59:59Z"
          }
        },
        "T3": {
          "probability": 0.305599,
          "alerts": {
            "0.5pct": false,
            "1.0pct": false,
            "2.0pct": false,
            "5.0pct": false,
            "10.0pct": false
          },
          "validity": {
            "window_days": 3,
            "valid_from": "2026-06-18T00:00:00Z",
            "valid_to": "2026-06-20T23:59:59Z"
          }
        },
        "T4": {
          "probability": 0.127664,
          "alerts": {
            "0.5pct": false,
            "1.0pct": false,
            "2.0pct": false,
            "5.0pct": false,
            "10.0pct": false
          },
          "validity": {
            "window_days": 3,
            "valid_from": "2026-06-18T00:00:00Z",
            "valid_to": "2026-06-20T23:59:59Z"
          }
        }
      }
    },
    {
      "zone_id": "Z_25_140",
      "name": "Z_25_140",
      "pop_millions": 0,
      "tiers": {
        "T1": {
          "probability": 0.177523,
          "alerts": {
            "0.5pct": false,
            "1.0pct": false,
            "2.0pct": false,
            "5.0pct": false,
            "10.0pct": false
          },
          "validity": {
            "window_days": 2,
            "valid_from": "2026-06-18T00:00:00Z",
            "valid_to": "2026-06-19T23:59:59Z"
          },
          "probability_seismic": 0.177523,
          "gps_reliability": 0.396,
          "boost": 0.0
        },
        "T2": {
          "probability": 0.371276,
          "alerts": {
            "0.5pct": false,
            "1.0pct": false,
            "2.0pct": false,
            "5.0pct": false,
            "10.0pct": false
          },
          "validity": {
            "window_days": 2,
            "valid_from": "2026-06-18T00:00:00Z",
            "valid_to": "2026-06-19T23:59:59Z"
          },
          "probability_seismic": 0.371276,
          "gps_reliability": 0.396,
          "boost": 0.0
        },
        "T3": {
          "probability": 0.359538,
          "alerts": {
            "0.5pct": false,
            "1.0pct": false,
            "2.0pct": false,
            "5.0pct": false,
            "10.0pct": false
          },
          "validity": {
            "window_days": 3,
            "valid_from": "2026-06-18T00:00:00Z",
            "valid_to": "2026-06-20T23:59:59Z"
          },
          "probability_seismic": 0.359538,
          "gps_reliability": 0.396,
          "boost": 0.0
        },
        "T4": {
          "probability": 0.333706,
          "alerts": {
            "0.5pct": false,
            "1.0pct": false,
            "2.0pct": false,
            "5.0pct": false,
            "10.0pct": false
          },
          "validity": {
            "window_days": 3,
            "valid_from": "2026-06-18T00:00:00Z",
            "valid_to": "2026-06-20T23:59:59Z"
          },
          "probability_seismic": 0.333706,
          "gps_reliability": 0.396,
          "boost": 0.0
        }
      }
    },
    {
      "zone_id": "Z_30_125",
      "name": "Z_30_125",
      "pop_millions": 0,
      "tiers": {
        "T1": {
          "probability": 0.213624,
          "alerts": {
            "0.5pct": false,
            "1.0pct": false,
            "2.0pct": false,
            "5.0pct": false,
            "10.0pct": false
          },
          "validity": {
            "window_days": 2,
            "valid_from": "2026-06-18T00:00:00Z",
            "valid_to": "2026-06-19T23:59:59Z"
          },
          "probability_seismic": 0.213624,
          "gps_reliability": 1.0,
          "boost": 0.0
        },
        "T2": {
          "probability": 0.264529,
          "alerts": {
            "0.5pct": false,
            "1.0pct": false,
            "2.0pct": true,
            "5.0pct": true,
            "10.0pct": true
          },
          "validity": {
            "window_days": 2,
            "valid_from": "2026-06-18T00:00:00Z",
            "valid_to": "2026-06-19T23:59:59Z"
          },
          "probability_seismic": 0.264529,
          "gps_reliability": 1.0,
          "boost": 0.0
        },
        "T3": {
          "probability": 0.059696,
          "alerts": {
            "0.5pct": false,
            "1.0pct": false,
            "2.0pct": false,
            "5.0pct": false,
            "10.0pct": false
          },
          "validity": {
            "window_days": 3,
            "valid_from": "2026-06-18T00:00:00Z",
            "valid_to": "2026-06-20T23:59:59Z"
          },
          "probability_seismic": 0.059696,
          "gps_reliability": 1.0,
          "boost": 0.0
        },
        "T4": {
          "probability": 0.013335,
          "alerts": {
            "0.5pct": false,
            "1.0pct": false,
            "2.0pct": false,
            "5.0pct": false,
            "10.0pct": false
          },
          "validity": {
            "window_days": 3,
            "valid_from": "2026-06-18T00:00:00Z",
            "valid_to": "2026-06-20T23:59:59Z"
          },
          "probability_seismic": 0.013335,
          "gps_reliability": 1.0,
          "boost": 0.0
        }
      }
    },
    {
      "zone_id": "Z_30_130",
      "name": "Kyushu-South",
      "pop_millions": 13,
      "tiers": {
        "T1": {
          "probability": 0.296921,
          "alerts": {
            "0.5pct": false,
            "1.0pct": false,
            "2.0pct": false,
            "5.0pct": false,
            "10.0pct": false
          },
          "validity": {
            "window_days": 2,
            "valid_from": "2026-06-18T00:00:00Z",
            "valid_to": "2026-06-19T23:59:59Z"
          },
          "probability_seismic": 0.296921,
          "gps_reliability": 0.58,
          "boost": 0.0
        },
        "T2": {
          "probability": 0.147922,
          "alerts": {
            "0.5pct": false,
            "1.0pct": false,
            "2.0pct": false,
            "5.0pct": false,
            "10.0pct": false
          },
          "validity": {
            "window_days": 2,
            "valid_from": "2026-06-18T00:00:00Z",
            "valid_to": "2026-06-19T23:59:59Z"
          },
          "probability_seismic": 0.147922,
          "gps_reliability": 0.58,
          "boost": 0.0
        },
        "T3": {
          "probability": 0.017864,
          "alerts": {
            "0.5pct": false,
            "1.0pct": false,
            "2.0pct": false,
            "5.0pct": false,
            "10.0pct": false
          },
          "validity": {
            "window_days": 3,
            "valid_from": "2026-06-18T00:00:00Z",
            "valid_to": "2026-06-20T23:59:59Z"
          },
          "probability_seismic": 0.017864,
          "gps_reliability": 0.58,
          "boost": 0.0
        },
        "T4": {
          "probability": 0.003384,
          "alerts": {
            "0.5pct": false,
            "1.0pct": false,
            "2.0pct": false,
            "5.0pct": false,
            "10.0pct": false
          },
          "validity": {
            "window_days": 3,
            "valid_from": "2026-06-18T00:00:00Z",
            "valid_to": "2026-06-20T23:59:59Z"
          },
          "probability_seismic": 0.003384,
          "gps_reliability": 0.58,
          "boost": -0.0
        }
      }
    },
    {
      "zone_id": "Z_30_135",
      "name": "Kyushu-North",
      "pop_millions": 4,
      "tiers": {
        "T1": {
          "probability": 0.281307,
          "alerts": {
            "0.5pct": false,
            "1.0pct": false,
            "2.0pct": false,
            "5.0pct": false,
            "10.0pct": false
          },
          "validity": {
            "window_days": 2,
            "valid_from": "2026-06-18T00:00:00Z",
            "valid_to": "2026-06-19T23:59:59Z"
          },
          "probability_seismic": 0.281307,
          "gps_reliability": 0.25,
          "boost": 0.0
        },
        "T2": {
          "probability": 0.244616,
          "alerts": {
            "0.5pct": false,
            "1.0pct": false,
            "2.0pct": false,
            "5.0pct": false,
            "10.0pct": false
          },
          "validity": {
            "window_days": 2,
            "valid_from": "2026-06-18T00:00:00Z",
            "valid_to": "2026-06-19T23:59:59Z"
          },
          "probability_seismic": 0.244616,
          "gps_reliability": 0.25,
          "boost": 0.0
        },
        "T3": {
          "probability": 0.047534,
          "alerts": {
            "0.5pct": false,
            "1.0pct": false,
            "2.0pct": false,
            "5.0pct": false,
            "10.0pct": false
          },
          "validity": {
            "window_days": 3,
            "valid_from": "2026-06-18T00:00:00Z",
            "valid_to": "2026-06-20T23:59:59Z"
          },
          "probability_seismic": 0.047534,
          "gps_reliability": 0.25,
          "boost": -0.0
        },
        "T4": {
          "probability": 0.012349,
          "alerts": {
            "0.5pct": false,
            "1.0pct": false,
            "2.0pct": false,
            "5.0pct": false,
            "10.0pct": false
          },
          "validity": {
            "window_days": 3,
            "valid_from": "2026-06-18T00:00:00Z",
            "valid_to": "2026-06-20T23:59:59Z"
          },
          "probability_seismic": 0.012349,
          "gps_reliability": 0.25,
          "boost": 0.0
        }
      }
    },
    {
      "zone_id": "Z_30_140",
      "name": "Z_30_140",
      "pop_millions": 0,
      "tiers": {
        "T1": {
          "probability": 0.484196,
          "alerts": {
            "0.5pct": false,
            "1.0pct": false,
            "2.0pct": false,
            "5.0pct": false,
            "10.0pct": false
          },
          "validity": {
            "window_days": 2,
            "valid_from": "2026-06-18T00:00:00Z",
            "valid_to": "2026-06-19T23:59:59Z"
          }
        },
        "T2": {
          "probability": 0.346915,
          "alerts": {
            "0.5pct": false,
            "1.0pct": false,
            "2.0pct": false,
            "5.0pct": false,
            "10.0pct": false
          },
          "validity": {
            "window_days": 2,
            "valid_from": "2026-06-18T00:00:00Z",
            "valid_to": "2026-06-19T23:59:59Z"
          }
        },
        "T3": {
          "probability": 0.180117,
          "alerts": {
            "0.5pct": false,
            "1.0pct": false,
            "2.0pct": false,
            "5.0pct": false,
            "10.0pct": false
          },
          "validity": {
            "window_days": 3,
            "valid_from": "2026-06-18T00:00:00Z",
            "valid_to": "2026-06-20T23:59:59Z"
          }
        },
        "T4": {
          "probability": 0.078524,
          "alerts": {
            "0.5pct": false,
            "1.0pct": false,
            "2.0pct": false,
            "5.0pct": false,
            "10.0pct": false
          },
          "validity": {
            "window_days": 3,
            "valid_from": "2026-06-18T00:00:00Z",
            "valid_to": "2026-06-20T23:59:59Z"
          }
        }
      }
    },
    {
      "zone_id": "Z_35_130",
      "name": "Shikoku",
      "pop_millions": 8,
      "tiers": {
        "T1": {
          "probability": 0.270223,
          "alerts": {
            "0.5pct": false,
            "1.0pct": false,
            "2.0pct": false,
            "5.0pct": false,
            "10.0pct": false
          },
          "validity": {
            "window_days": 2,
            "valid_from": "2026-06-18T00:00:00Z",
            "valid_to": "2026-06-19T23:59:59Z"
          },
          "probability_seismic": 0.270223,
          "gps_reliability": 0.25,
          "boost": 0.0
        },
        "T2": {
          "probability": 0.349251,
          "alerts": {
            "0.5pct": false,
            "1.0pct": false,
            "2.0pct": true,
            "5.0pct": true,
            "10.0pct": true
          },
          "validity": {
            "window_days": 2,
            "valid_from": "2026-06-18T00:00:00Z",
            "valid_to": "2026-06-19T23:59:59Z"
          },
          "probability_seismic": 0.349251,
          "gps_reliability": 0.25,
          "boost": 0.0
        },
        "T3": {
          "probability": 0.304448,
          "alerts": {
            "0.5pct": false,
            "1.0pct": false,
            "2.0pct": false,
            "5.0pct": true,
            "10.0pct": true
          },
          "validity": {
            "window_days": 3,
            "valid_from": "2026-06-18T00:00:00Z",
            "valid_to": "2026-06-20T23:59:59Z"
          },
          "probability_seismic": 0.304448,
          "gps_reliability": 0.25,
          "boost": 0.0
        },
        "T4": {
          "probability": 0.278472,
          "alerts": {
            "0.5pct": false,
            "1.0pct": false,
            "2.0pct": false,
            "5.0pct": false,
            "10.0pct": true
          },
          "validity": {
            "window_days": 3,
            "valid_from": "2026-06-18T00:00:00Z",
            "valid_to": "2026-06-20T23:59:59Z"
          },
          "probability_seismic": 0.278472,
          "gps_reliability": 0.25,
          "boost": 0.0
        }
      }
    },
    {
      "zone_id": "Z_35_135",
      "name": "Osaka-Kobe",
      "pop_millions": 60,
      "tiers": {
        "T1": {
          "probability": 0.444348,
          "alerts": {
            "0.5pct": false,
            "1.0pct": false,
            "2.0pct": false,
            "5.0pct": false,
            "10.0pct": false
          },
          "validity": {
            "window_days": 2,
            "valid_from": "2026-06-18T00:00:00Z",
            "valid_to": "2026-06-19T23:59:59Z"
          },
          "probability_seismic": 0.444348,
          "gps_reliability": 0.646,
          "boost": 0.0
        },
        "T2": {
          "probability": 0.262193,
          "alerts": {
            "0.5pct": false,
            "1.0pct": false,
            "2.0pct": false,
            "5.0pct": false,
            "10.0pct": false
          },
          "validity": {
            "window_days": 2,
            "valid_from": "2026-06-18T00:00:00Z",
            "valid_to": "2026-06-19T23:59:59Z"
          },
          "probability_seismic": 0.262193,
          "gps_reliability": 0.646,
          "boost": -0.0
        },
        "T3": {
          "probability": 0.127736,
          "alerts": {
            "0.5pct": false,
            "1.0pct": false,
            "2.0pct": false,
            "5.0pct": false,
            "10.0pct": false
          },
          "validity": {
            "window_days": 3,
            "valid_from": "2026-06-18T00:00:00Z",
            "valid_to": "2026-06-20T23:59:59Z"
          },
          "probability_seismic": 0.127736,
          "gps_reliability": 0.646,
          "boost": 0.0
        },
        "T4": {
          "probability": 0.014279,
          "alerts": {
            "0.5pct": false,
            "1.0pct": false,
            "2.0pct": false,
            "5.0pct": false,
            "10.0pct": false
          },
          "validity": {
            "window_days": 3,
            "valid_from": "2026-06-18T00:00:00Z",
            "valid_to": "2026-06-20T23:59:59Z"
          },
          "probability_seismic": 0.014279,
          "gps_reliability": 0.646,
          "boost": 0.0
        }
      }
    },
    {
      "zone_id": "Z_35_140",
      "name": "Tokyo-Kanto",
      "pop_millions": 39,
      "tiers": {
        "T1": {
          "probability": 0.775328,
          "alerts": {
            "0.5pct": false,
            "1.0pct": false,
            "2.0pct": false,
            "5.0pct": false,
            "10.0pct": false
          },
          "validity": {
            "window_days": 2,
            "valid_from": "2026-06-18T00:00:00Z",
            "valid_to": "2026-06-19T23:59:59Z"
          },
          "probability_seismic": 0.775328,
          "gps_reliability": 0.396,
          "boost": 0.0
        },
        "T2": {
          "probability": 0.430035,
          "alerts": {
            "0.5pct": false,
            "1.0pct": false,
            "2.0pct": false,
            "5.0pct": false,
            "10.0pct": false
          },
          "validity": {
            "window_days": 2,
            "valid_from": "2026-06-18T00:00:00Z",
            "valid_to": "2026-06-19T23:59:59Z"
          },
          "probability_seismic": 0.430035,
          "gps_reliability": 0.396,
          "boost": 0.0
        },
        "T3": {
          "probability": 0.170023,
          "alerts": {
            "0.5pct": false,
            "1.0pct": false,
            "2.0pct": false,
            "5.0pct": false,
            "10.0pct": false
          },
          "validity": {
            "window_days": 3,
            "valid_from": "2026-06-18T00:00:00Z",
            "valid_to": "2026-06-20T23:59:59Z"
          },
          "probability_seismic": 0.170023,
          "gps_reliability": 0.396,
          "boost": -0.0
        },
        "T4": {
          "probability": 0.018473,
          "alerts": {
            "0.5pct": false,
            "1.0pct": false,
            "2.0pct": false,
            "5.0pct": false,
            "10.0pct": false
          },
          "validity": {
            "window_days": 3,
            "valid_from": "2026-06-18T00:00:00Z",
            "valid_to": "2026-06-20T23:59:59Z"
          },
          "probability_seismic": 0.018473,
          "gps_reliability": 0.396,
          "boost": -0.0
        }
      }
    },
    {
      "zone_id": "Z_40_130",
      "name": "Z_40_130",
      "pop_millions": 0,
      "tiers": {
        "T1": {
          "probability": 0.006804,
          "alerts": {
            "0.5pct": false,
            "1.0pct": false,
            "2.0pct": false,
            "5.0pct": false,
            "10.0pct": false
          },
          "validity": {
            "window_days": 2,
            "valid_from": "2026-06-18T00:00:00Z",
            "valid_to": "2026-06-19T23:59:59Z"
          },
          "probability_seismic": 0.006804,
          "gps_reliability": 0.25,
          "boost": -0.0
        },
        "T2": {
          "probability": 0.12932,
          "alerts": {
            "0.5pct": false,
            "1.0pct": false,
            "2.0pct": false,
            "5.0pct": false,
            "10.0pct": false
          },
          "validity": {
            "window_days": 2,
            "valid_from": "2026-06-18T00:00:00Z",
            "valid_to": "2026-06-19T23:59:59Z"
          },
          "probability_seismic": 0.12932,
          "gps_reliability": 0.25,
          "boost": 0.0
        },
        "T3": {
          "probability": 0.293449,
          "alerts": {
            "0.5pct": false,
            "1.0pct": false,
            "2.0pct": false,
            "5.0pct": false,
            "10.0pct": false
          },
          "validity": {
            "window_days": 3,
            "valid_from": "2026-06-18T00:00:00Z",
            "valid_to": "2026-06-20T23:59:59Z"
          },
          "probability_seismic": 0.293449,
          "gps_reliability": 0.25,
          "boost": 0.0
        },
        "T4": {
          "probability": 0.322696,
          "alerts": {
            "0.5pct": false,
            "1.0pct": false,
            "2.0pct": false,
            "5.0pct": false,
            "10.0pct": false
          },
          "validity": {
            "window_days": 3,
            "valid_from": "2026-06-18T00:00:00Z",
            "valid_to": "2026-06-20T23:59:59Z"
          },
          "probability_seismic": 0.322696,
          "gps_reliability": 0.25,
          "boost": 0.0
        }
      }
    },
    {
      "zone_id": "Z_40_135",
      "name": "Niigata",
      "pop_millions": 8,
      "tiers": {
        "T1": {
          "probability": 0.243431,
          "alerts": {
            "0.5pct": false,
            "1.0pct": false,
            "2.0pct": false,
            "5.0pct": false,
            "10.0pct": false
          },
          "validity": {
            "window_days": 2,
            "valid_from": "2026-06-18T00:00:00Z",
            "valid_to": "2026-06-19T23:59:59Z"
          },
          "probability_seismic": 0.243431,
          "gps_reliability": 0.25,
          "boost": -0.0
        },
        "T2": {
          "probability": 0.111456,
          "alerts": {
            "0.5pct": false,
            "1.0pct": false,
            "2.0pct": false,
            "5.0pct": false,
            "10.0pct": false
          },
          "validity": {
            "window_days": 2,
            "valid_from": "2026-06-18T00:00:00Z",
            "valid_to": "2026-06-19T23:59:59Z"
          },
          "probability_seismic": 0.111456,
          "gps_reliability": 0.25,
          "boost": 0.0
        },
        "T3": {
          "probability": 0.015523,
          "alerts": {
            "0.5pct": false,
            "1.0pct": false,
            "2.0pct": false,
            "5.0pct": false,
            "10.0pct": false
          },
          "validity": {
            "window_days": 3,
            "valid_from": "2026-06-18T00:00:00Z",
            "valid_to": "2026-06-20T23:59:59Z"
          },
          "probability_seismic": 0.015523,
          "gps_reliability": 0.25,
          "boost": -0.0
        },
        "T4": {
          "probability": 0.000528,
          "alerts": {
            "0.5pct": false,
            "1.0pct": false,
            "2.0pct": false,
            "5.0pct": false,
            "10.0pct": false
          },
          "validity": {
            "window_days": 3,
            "valid_from": "2026-06-18T00:00:00Z",
            "valid_to": "2026-06-20T23:59:59Z"
          },
          "probability_seismic": 0.000528,
          "gps_reliability": 0.25,
          "boost": 0.0
        }
      }
    },
    {
      "zone_id": "Z_40_140",
      "name": "Hokkaido-S",
      "pop_millions": 4,
      "tiers": {
        "T1": {
          "probability": 0.482668,
          "alerts": {
            "0.5pct": false,
            "1.0pct": false,
            "2.0pct": false,
            "5.0pct": false,
            "10.0pct": false
          },
          "validity": {
            "window_days": 2,
            "valid_from": "2026-06-18T00:00:00Z",
            "valid_to": "2026-06-19T23:59:59Z"
          },
          "probability_seismic": 0.482668,
          "gps_reliability": 0.58,
          "boost": 0.0
        },
        "T2": {
          "probability": 0.452019,
          "alerts": {
            "0.5pct": false,
            "1.0pct": false,
            "2.0pct": false,
            "5.0pct": false,
            "10.0pct": false
          },
          "validity": {
            "window_days": 2,
            "valid_from": "2026-06-18T00:00:00Z",
            "valid_to": "2026-06-19T23:59:59Z"
          },
          "probability_seismic": 0.452019,
          "gps_reliability": 0.58,
          "boost": 0.0
        },
        "T3": {
          "probability": 0.342423,
          "alerts": {
            "0.5pct": false,
            "1.0pct": false,
            "2.0pct": false,
            "5.0pct": false,
            "10.0pct": false
          },
          "validity": {
            "window_days": 3,
            "valid_from": "2026-06-18T00:00:00Z",
            "valid_to": "2026-06-20T23:59:59Z"
          },
          "probability_seismic": 0.342423,
          "gps_reliability": 0.58,
          "boost": 0.0
        },
        "T4": {
          "probability": 0.177791,
          "alerts": {
            "0.5pct": false,
            "1.0pct": false,
            "2.0pct": false,
            "5.0pct": false,
            "10.0pct": false
          },
          "validity": {
            "window_days": 3,
            "valid_from": "2026-06-18T00:00:00Z",
            "valid_to": "2026-06-20T23:59:59Z"
          },
          "probability_seismic": 0.177791,
          "gps_reliability": 0.58,
          "boost": 0.0
        }
      }
    },
    {
      "zone_id": "Z_40_145",
      "name": "Hokkaido-E",
      "pop_millions": 5,
      "tiers": {
        "T1": {
          "probability": 0.490079,
          "alerts": {
            "0.5pct": false,
            "1.0pct": false,
            "2.0pct": false,
            "5.0pct": false,
            "10.0pct": false
          },
          "validity": {
            "window_days": 2,
            "valid_from": "2026-06-18T00:00:00Z",
            "valid_to": "2026-06-19T23:59:59Z"
          },
          "probability_seismic": 0.490079,
          "gps_reliability": 0.925,
          "boost": 0.0
        },
        "T2": {
          "probability": 0.31134,
          "alerts": {
            "0.5pct": false,
            "1.0pct": false,
            "2.0pct": false,
            "5.0pct": false,
            "10.0pct": false
          },
          "validity": {
            "window_days": 2,
            "valid_from": "2026-06-18T00:00:00Z",
            "valid_to": "2026-06-19T23:59:59Z"
          },
          "probability_seismic": 0.31134,
          "gps_reliability": 0.925,
          "boost": 0.0
        },
        "T3": {
          "probability": 0.034842,
          "alerts": {
            "0.5pct": false,
            "1.0pct": false,
            "2.0pct": false,
            "5.0pct": false,
            "10.0pct": false
          },
          "validity": {
            "window_days": 3,
            "valid_from": "2026-06-18T00:00:00Z",
            "valid_to": "2026-06-20T23:59:59Z"
          },
          "probability_seismic": 0.034842,
          "gps_reliability": 0.925,
          "boost": -0.0
        },
        "T4": {
          "probability": 7.8e-05,
          "alerts": {
            "0.5pct": false,
            "1.0pct": false,
            "2.0pct": false,
            "5.0pct": false,
            "10.0pct": false
          },
          "validity": {
            "window_days": 3,
            "valid_from": "2026-06-18T00:00:00Z",
            "valid_to": "2026-06-20T23:59:59Z"
          },
          "probability_seismic": 7.8e-05,
          "gps_reliability": 0.925,
          "boost": -0.0
        }
      }
    },
    {
      "zone_id": "Z_40_150",
      "name": "Z_40_150",
      "pop_millions": 0,
      "tiers": {
        "T1": {
          "probability": 0.006844,
          "alerts": {
            "0.5pct": false,
            "1.0pct": false,
            "2.0pct": false,
            "5.0pct": false,
            "10.0pct": false
          },
          "validity": {
            "window_days": 2,
            "valid_from": "2026-06-18T00:00:00Z",
            "valid_to": "2026-06-19T23:59:59Z"
          }
        },
        "T2": {
          "probability": 0.129809,
          "alerts": {
            "0.5pct": false,
            "1.0pct": false,
            "2.0pct": false,
            "5.0pct": false,
            "10.0pct": false
          },
          "validity": {
            "window_days": 2,
            "valid_from": "2026-06-18T00:00:00Z",
            "valid_to": "2026-06-19T23:59:59Z"
          }
        },
        "T3": {
          "probability": 0.293832,
          "alerts": {
            "0.5pct": false,
            "1.0pct": false,
            "2.0pct": false,
            "5.0pct": false,
            "10.0pct": false
          },
          "validity": {
            "window_days": 3,
            "valid_from": "2026-06-18T00:00:00Z",
            "valid_to": "2026-06-20T23:59:59Z"
          }
        },
        "T4": {
          "probability": 0.323,
          "alerts": {
            "0.5pct": false,
            "1.0pct": false,
            "2.0pct": false,
            "5.0pct": false,
            "10.0pct": false
          },
          "validity": {
            "window_days": 3,
            "valid_from": "2026-06-18T00:00:00Z",
            "valid_to": "2026-06-20T23:59:59Z"
          }
        }
      }
    },
    {
      "zone_id": "Z_45_140",
      "name": "Z_45_140",
      "pop_millions": 0,
      "tiers": {
        "T1": {
          "probability": 0.029206,
          "alerts": {
            "0.5pct": false,
            "1.0pct": false,
            "2.0pct": false,
            "5.0pct": false,
            "10.0pct": false
          },
          "validity": {
            "window_days": 2,
            "valid_from": "2026-06-18T00:00:00Z",
            "valid_to": "2026-06-19T23:59:59Z"
          },
          "probability_seismic": 0.029206,
          "gps_reliability": 0.25,
          "boost": 0.0
        },
        "T2": {
          "probability": 0.21916,
          "alerts": {
            "0.5pct": false,
            "1.0pct": false,
            "2.0pct": false,
            "5.0pct": false,
            "10.0pct": false
          },
          "validity": {
            "window_days": 2,
            "valid_from": "2026-06-18T00:00:00Z",
            "valid_to": "2026-06-19T23:59:59Z"
          },
          "probability_seismic": 0.21916,
          "gps_reliability": 0.25,
          "boost": 0.0
        },
        "T3": {
          "probability": 0.341863,
          "alerts": {
            "0.5pct": false,
            "1.0pct": false,
            "2.0pct": false,
            "5.0pct": false,
            "10.0pct": false
          },
          "validity": {
            "window_days": 3,
            "valid_from": "2026-06-18T00:00:00Z",
            "valid_to": "2026-06-20T23:59:59Z"
          },
          "probability_seismic": 0.341863,
          "gps_reliability": 0.25,
          "boost": 0.0
        },
        "T4": {
          "probability": 0.361155,
          "alerts": {
            "0.5pct": false,
            "1.0pct": false,
            "2.0pct": false,
            "5.0pct": true,
            "10.0pct": true
          },
          "validity": {
            "window_days": 3,
            "valid_from": "2026-06-18T00:00:00Z",
            "valid_to": "2026-06-20T23:59:59Z"
          },
          "probability_seismic": 0.361155,
          "gps_reliability": 0.25,
          "boost": 0.0
        }
      }
    },
    {
      "zone_id": "Z_45_145",
      "name": "Kuril-South",
      "pop_millions": 5,
      "tiers": {
        "T1": {
          "probability": 0.016975,
          "alerts": {
            "0.5pct": false,
            "1.0pct": false,
            "2.0pct": false,
            "5.0pct": false,
            "10.0pct": false
          },
          "validity": {
            "window_days": 2,
            "valid_from": "2026-06-18T00:00:00Z",
            "valid_to": "2026-06-19T23:59:59Z"
          },
          "probability_seismic": 0.016975,
          "gps_reliability": 0.25,
          "boost": 0.0
        },
        "T2": {
          "probability": 0.162242,
          "alerts": {
            "0.5pct": false,
            "1.0pct": false,
            "2.0pct": false,
            "5.0pct": false,
            "10.0pct": false
          },
          "validity": {
            "window_days": 2,
            "valid_from": "2026-06-18T00:00:00Z",
            "valid_to": "2026-06-19T23:59:59Z"
          },
          "probability_seismic": 0.162242,
          "gps_reliability": 0.25,
          "boost": 0.0
        },
        "T3": {
          "probability": 0.321761,
          "alerts": {
            "0.5pct": false,
            "1.0pct": false,
            "2.0pct": false,
            "5.0pct": false,
            "10.0pct": false
          },
          "validity": {
            "window_days": 3,
            "valid_from": "2026-06-18T00:00:00Z",
            "valid_to": "2026-06-20T23:59:59Z"
          },
          "probability_seismic": 0.321761,
          "gps_reliability": 0.25,
          "boost": 0.0
        },
        "T4": {
          "probability": 0.354603,
          "alerts": {
            "0.5pct": false,
            "1.0pct": false,
            "2.0pct": false,
            "5.0pct": false,
            "10.0pct": false
          },
          "validity": {
            "window_days": 3,
            "valid_from": "2026-06-18T00:00:00Z",
            "valid_to": "2026-06-20T23:59:59Z"
          },
          "probability_seismic": 0.354603,
          "gps_reliability": 0.25,
          "boost": -0.0
        }
      }
    },
    {
      "zone_id": "Z_45_150",
      "name": "Z_45_150",
      "pop_millions": 0,
      "tiers": {
        "T1": {
          "probability": 0.109498,
          "alerts": {
            "0.5pct": false,
            "1.0pct": false,
            "2.0pct": false,
            "5.0pct": false,
            "10.0pct": false
          },
          "validity": {
            "window_days": 2,
            "valid_from": "2026-06-18T00:00:00Z",
            "valid_to": "2026-06-19T23:59:59Z"
          }
        },
        "T2": {
          "probability": 0.319459,
          "alerts": {
            "0.5pct": false,
            "1.0pct": false,
            "2.0pct": false,
            "5.0pct": false,
            "10.0pct": false
          },
          "validity": {
            "window_days": 2,
            "valid_from": "2026-06-18T00:00:00Z",
            "valid_to": "2026-06-19T23:59:59Z"
          }
        },
        "T3": {
          "probability": 0.321848,
          "alerts": {
            "0.5pct": false,
            "1.0pct": false,
            "2.0pct": false,
            "5.0pct": false,
            "10.0pct": false
          },
          "validity": {
            "window_days": 3,
            "valid_from": "2026-06-18T00:00:00Z",
            "valid_to": "2026-06-20T23:59:59Z"
          }
        },
        "T4": {
          "probability": 0.316917,
          "alerts": {
            "0.5pct": false,
            "1.0pct": false,
            "2.0pct": false,
            "5.0pct": false,
            "10.0pct": false
          },
          "validity": {
            "window_days": 3,
            "valid_from": "2026-06-18T00:00:00Z",
            "valid_to": "2026-06-20T23:59:59Z"
          }
        }
      }
    },
    {
      "zone_id": "Z_45_155",
      "name": "Z_45_155",
      "pop_millions": 0,
      "tiers": {
        "T1": {
          "probability": 0.006793,
          "alerts": {
            "0.5pct": false,
            "1.0pct": false,
            "2.0pct": false,
            "5.0pct": false,
            "10.0pct": false
          },
          "validity": {
            "window_days": 2,
            "valid_from": "2026-06-18T00:00:00Z",
            "valid_to": "2026-06-19T23:59:59Z"
          }
        },
        "T2": {
          "probability": 0.129395,
          "alerts": {
            "0.5pct": false,
            "1.0pct": false,
            "2.0pct": false,
            "5.0pct": false,
            "10.0pct": false
          },
          "validity": {
            "window_days": 2,
            "valid_from": "2026-06-18T00:00:00Z",
            "valid_to": "2026-06-19T23:59:59Z"
          }
        },
        "T3": {
          "probability": 0.293411,
          "alerts": {
            "0.5pct": false,
            "1.0pct": false,
            "2.0pct": false,
            "5.0pct": false,
            "10.0pct": false
          },
          "validity": {
            "window_days": 3,
            "valid_from": "2026-06-18T00:00:00Z",
            "valid_to": "2026-06-20T23:59:59Z"
          }
        },
        "T4": {
          "probability": 0.322594,
          "alerts": {
            "0.5pct": false,
            "1.0pct": false,
            "2.0pct": false,
            "5.0pct": false,
            "10.0pct": false
          },
          "validity": {
            "window_days": 3,
            "valid_from": "2026-06-18T00:00:00Z",
            "valid_to": "2026-06-20T23:59:59Z"
          }
        }
      }
    },
    {
      "zone_id": "Z_50_150",
      "name": "Z_50_150",
      "pop_millions": 0,
      "tiers": {
        "T1": {
          "probability": 0.006721,
          "alerts": {
            "0.5pct": false,
            "1.0pct": false,
            "2.0pct": false,
            "5.0pct": false,
            "10.0pct": false
          },
          "validity": {
            "window_days": 2,
            "valid_from": "2026-06-18T00:00:00Z",
            "valid_to": "2026-06-19T23:59:59Z"
          }
        },
        "T2": {
          "probability": 0.128738,
          "alerts": {
            "0.5pct": false,
            "1.0pct": false,
            "2.0pct": false,
            "5.0pct": false,
            "10.0pct": false
          },
          "validity": {
            "window_days": 2,
            "valid_from": "2026-06-18T00:00:00Z",
            "valid_to": "2026-06-19T23:59:59Z"
          }
        },
        "T3": {
          "probability": 0.292799,
          "alerts": {
            "0.5pct": false,
            "1.0pct": false,
            "2.0pct": false,
            "5.0pct": false,
            "10.0pct": false
          },
          "validity": {
            "window_days": 3,
            "valid_from": "2026-06-18T00:00:00Z",
            "valid_to": "2026-06-20T23:59:59Z"
          }
        },
        "T4": {
          "probability": 0.322037,
          "alerts": {
            "0.5pct": false,
            "1.0pct": false,
            "2.0pct": false,
            "5.0pct": false,
            "10.0pct": false
          },
          "validity": {
            "window_days": 3,
            "valid_from": "2026-06-18T00:00:00Z",
            "valid_to": "2026-06-20T23:59:59Z"
          }
        }
      }
    },
    {
      "zone_id": "Z_50_155",
      "name": "Z_50_155",
      "pop_millions": 0,
      "tiers": {
        "T1": {
          "probability": 0.006731,
          "alerts": {
            "0.5pct": false,
            "1.0pct": false,
            "2.0pct": false,
            "5.0pct": false,
            "10.0pct": false
          },
          "validity": {
            "window_days": 2,
            "valid_from": "2026-06-18T00:00:00Z",
            "valid_to": "2026-06-19T23:59:59Z"
          },
          "probability_seismic": 0.006731,
          "gps_reliability": 0.25,
          "boost": 0.0
        },
        "T2": {
          "probability": 0.12886,
          "alerts": {
            "0.5pct": false,
            "1.0pct": false,
            "2.0pct": false,
            "5.0pct": false,
            "10.0pct": false
          },
          "validity": {
            "window_days": 2,
            "valid_from": "2026-06-18T00:00:00Z",
            "valid_to": "2026-06-19T23:59:59Z"
          },
          "probability_seismic": 0.12886,
          "gps_reliability": 0.25,
          "boost": 0.0
        },
        "T3": {
          "probability": 0.292895,
          "alerts": {
            "0.5pct": false,
            "1.0pct": false,
            "2.0pct": false,
            "5.0pct": false,
            "10.0pct": false
          },
          "validity": {
            "window_days": 3,
            "valid_from": "2026-06-18T00:00:00Z",
            "valid_to": "2026-06-20T23:59:59Z"
          },
          "probability_seismic": 0.292895,
          "gps_reliability": 0.25,
          "boost": 0.0
        },
        "T4": {
          "probability": 0.322113,
          "alerts": {
            "0.5pct": false,
            "1.0pct": false,
            "2.0pct": false,
            "5.0pct": false,
            "10.0pct": false
          },
          "validity": {
            "window_days": 3,
            "valid_from": "2026-06-18T00:00:00Z",
            "valid_to": "2026-06-20T23:59:59Z"
          },
          "probability_seismic": 0.322113,
          "gps_reliability": 0.25,
          "boost": 0.0
        }
      }
    }
  ],
  "summary": {
    "total_zones": 29,
    "alerts_by_tier": {
      "T1": 1,
      "T2": 3,
      "T3": 1,
      "T4": 2
    }
  }
}